{"config": {"view": {"continuousWidth": 400, "continuousHeight": 300}}, "layer": [{"mark": "bar", "encoding": {"color": {"field": "restake_earnings", "legend": {"direction": "vertical", "fillColor": "white", "labelFontSize": 9, "legendX": 100, "legendY": 400, "orient": "none", "padding": 5, "strokeColor": "gray", "title": "Restake Earnings", "titleAnchor": "start"}, "scale": {"domain": ["true", "false"], "range": ["#70B785", "#549FF2"]}, "type": "nominal"}, "x": {"field": "staked_amount", "title": "Staked Amount", "type": "quantitative"}, "y": {"field": "order", "title": null, "type": "ordinal"}}}, {"mark": {"type": "text", "align": "left", "baseline": "middle", "dx": 10, "dy": 2}, "encoding": {"color": {"field": "restake_earnings", "legend": {"direction": "vertical", "fillColor": "white", "labelFontSize": 9, "legendX": 100, "legendY": 400, "orient": "none", "padding": 5, "strokeColor": "gray", "title": "Restake Earnings", "titleAnchor": "start"}, "scale": {"domain": ["true", "false"], "range": ["#70B785", "#549FF2"]}, "type": "nominal"}, "text": {"field": "baker_id", "type": "ordinal"}, "x": {"field": "staked_amount", "title": "Staked Amount", "type": "quantitative"}, "y": {"field": "order", "title": null, "type": "ordinal"}}}], "data": {"name": "data-2f185e29e421bf9497b65a9f893a32f3"}, "height": 500, "title": {"text": "Baker accounts (top 50) - Staked amounts", "subtitle": "2022-08-09"}, "width": "container", "$schema": "https://vega.github.io/schema/vega-lite/v4.17.0.json", "datasets": {"data-2f185e29e421bf9497b65a9f893a32f3": [{"index": 37387, "account": "3ofwYFAkgV59BsHqzmiWyRmmKRB5ZzrPfbmx5nup24cE53jNX5", "nonce": 2, "credential_creation_date": "2021-05-01", "credential_valid_to_date": "2026-05-01", "credential_count": 7, "total_balance": 885296161.826289, "unlocked_balance": 885296161.826289, "locked_balance": 0.0, "baker_id": 5.0, "staked_amount": 882921786.087564, "restake_earnings": true, "pool_status": "closedForAll", "pool_metadata_url": null, "pool_transaction_commission": 0.1, "pool_finalization_commission": 1.0, "pool_baking_commission": 0.1, "delegation_target": null, "baker_lp": 0.101562, "baker_bpy": "320,505.30", "o": 0, "order": 1}, {"index": 73161, "account": "4d13WVDNKVGDUxRUb1PRQAJyTwWSVcjWS7uwZ1oqmDm5icQEPT", "nonce": 2, "credential_creation_date": "2021-05-01", "credential_valid_to_date": "2026-05-01", "credential_count": 7, "total_balance": 765995738.019356, "unlocked_balance": 765995738.019356, "locked_balance": 0.0, "baker_id": 3.0, "staked_amount": 763656935.167495, "restake_earnings": true, "pool_status": "closedForAll", "pool_metadata_url": null, "pool_transaction_commission": 0.1, "pool_finalization_commission": 1.0, "pool_baking_commission": 0.1, "delegation_target": null, "baker_lp": 0.0964439999999999, "baker_bpy": "304,354.12", "o": 1, "order": 2}, {"index": 48636, "account": "44bxoGippBqpgseaiYPFnYgi5J5q58bQKfpQFeGbY9DHmDPD78", "nonce": 4, "credential_creation_date": "2021-05-01", "credential_valid_to_date": "2026-05-01", "credential_count": 7, "total_balance": 764119915.658609, "unlocked_balance": 764119915.658609, "locked_balance": 0.0, "baker_id": 8.0, "staked_amount": 763607960.806998, "restake_earnings": true, "pool_status": "closedForAll", "pool_metadata_url": null, "pool_transaction_commission": 0.1, "pool_finalization_commission": 1.0, "pool_baking_commission": 0.1, "delegation_target": null, "baker_lp": 0.096441, "baker_bpy": "304,344.65", "o": 2, "order": 3}, {"index": 12560, "account": "3EctbG8WaQkTqZb1NTJPAFnqmuhvW62pQbywvqb9VeyqaFZdzN", "nonce": 2, "credential_creation_date": "2021-05-01", "credential_valid_to_date": "2026-05-01", "credential_count": 7, "total_balance": 759933575.254415, "unlocked_balance": 759933575.254415, "locked_balance": 0.0, "baker_id": 4.0, "staked_amount": 757571249.833787, "restake_earnings": true, "pool_status": "closedForAll", "pool_metadata_url": null, "pool_transaction_commission": 0.1, "pool_finalization_commission": 1.0, "pool_baking_commission": 0.1, "delegation_target": null, "baker_lp": 0.095677, "baker_bpy": "301,933.65", "o": 3, "order": 4}, {"index": 51134, "account": "47xTHwtFra1d4Mq4DYZuZYJEYrDXY34C4CGkTTzT6eiwjEczuT", "nonce": 4, "credential_creation_date": "2021-05-01", "credential_valid_to_date": "2026-05-01", "credential_count": 7, "total_balance": 1037207888.381785, "unlocked_balance": 1037207888.381785, "locked_balance": 0.0, "baker_id": 1.0, "staked_amount": 692847270.204617, "restake_earnings": true, "pool_status": "closedForAll", "pool_metadata_url": null, "pool_transaction_commission": 0.1, "pool_finalization_commission": 1.0, "pool_baking_commission": 0.1, "delegation_target": null, "baker_lp": 0.087504, "baker_bpy": "276,141.62", "o": 4, "order": 5}, {"index": 67541, "account": "4VYm2qx7dViwhqobzznLBM4oeixZxDmWZ6pYCckczXePJ4ZvdZ", "nonce": 4, "credential_creation_date": "2022-04-01", "credential_valid_to_date": "2027-04-01", "credential_count": 4, "total_balance": 666708585.833262, "unlocked_balance": 125103914.448644, "locked_balance": 541604671.384618, "baker_id": 83078.0, "staked_amount": 666707529.387216, "restake_earnings": true, "pool_status": "closedForAll", "pool_metadata_url": null, "pool_transaction_commission": 0.1, "pool_finalization_commission": 1.0, "pool_baking_commission": 0.1, "delegation_target": null, "baker_lp": 0.0842029999999999, "baker_bpy": "265,724.46", "o": 5, "order": 6}, {"index": 36271, "account": "3nDiUUeTrHYrG2oqTCzz9tzg8SCpiR4LL7TFBjgKVEeBpkQEwE", "nonce": 5, "credential_creation_date": "2022-04-01", "credential_valid_to_date": "2027-04-01", "credential_count": 4, "total_balance": 664360923.159557, "unlocked_balance": 122756251.774939, "locked_balance": 541604671.384618, "baker_id": 83075.0, "staked_amount": 664359620.062766, "restake_earnings": true, "pool_status": "closedForAll", "pool_metadata_url": null, "pool_transaction_commission": 0.1, "pool_finalization_commission": 1.0, "pool_baking_commission": 0.1, "delegation_target": null, "baker_lp": 0.083906, "baker_bpy": "264,787.20", "o": 6, "order": 7}, {"index": 61314, "account": "4MPJybKC9Kz7kw9KNyLHhuAEt4ZTxLsd3DBDbxtKdUiv4fXqVN", "nonce": 1, "credential_creation_date": "2021-05-01", "credential_valid_to_date": "2026-05-01", "credential_count": 7, "total_balance": 647292396.61473, "unlocked_balance": 647292396.61473, "locked_balance": 0.0, "baker_id": 6.0, "staked_amount": 647291396.614729, "restake_earnings": true, "pool_status": "closedForAll", "pool_metadata_url": null, "pool_transaction_commission": 0.1, "pool_finalization_commission": 1.0, "pool_baking_commission": 0.1, "delegation_target": null, "baker_lp": 0.0817489999999999, "baker_bpy": "257,980.22", "o": 7, "order": 8}, {"index": 71076, "account": "4aLZNqgmdM1N5JJRd9h88idXypPbri6odXR9rMEuD7VQxTeGvv", "nonce": 6, "credential_creation_date": "2022-04-01", "credential_valid_to_date": "2027-04-01", "credential_count": 4, "total_balance": 366353390.173207, "unlocked_balance": 302052598.173207, "locked_balance": 64300792.0, "baker_id": 83079.0, "staked_amount": 366352882.633282, "restake_earnings": true, "pool_status": "closedForAll", "pool_metadata_url": null, "pool_transaction_commission": 0.1, "pool_finalization_commission": 1.0, "pool_baking_commission": 0.1, "delegation_target": null, "baker_lp": 0.046268, "baker_bpy": "146,010.70", "o": 8, "order": 9}, {"index": 82539, "account": "4qL7HmpqdKpYufCV7EvL1WnHVowy1CrTQS7jfYgef5stzpftwS", "nonce": 66, "credential_creation_date": "2022-01-01", "credential_valid_to_date": "2027-01-01", "credential_count": 1, "total_balance": 206295406.001031, "unlocked_balance": 26348813.351029, "locked_balance": 179946592.650002, "baker_id": 76670.0, "staked_amount": 206000000.0, "restake_earnings": false, "pool_status": "openForAll", "pool_metadata_url": null, "pool_transaction_commission": 0.1, "pool_finalization_commission": 1.0, "pool_baking_commission": 0.1, "delegation_target": null, "baker_lp": 0.0278129999999999, "baker_bpy": "87,771.15", "o": 9, "order": 10}, {"index": 25412, "account": "3Xhdwp4Y2dXTTKaCs1G4QNy7vtUtmZDRzwtex1hSqw2ekUK7ZE", "nonce": 17, "credential_creation_date": "2022-01-01", "credential_valid_to_date": "2027-01-01", "credential_count": 3, "total_balance": 168637744.160723, "unlocked_balance": 134963730.985162, "locked_balance": 33674013.175561, "baker_id": 72532.0, "staked_amount": 167978689.080405, "restake_earnings": true, "pool_status": "closedForAll", "pool_metadata_url": null, "pool_transaction_commission": 0.1, "pool_finalization_commission": 1.0, "pool_baking_commission": 0.1, "delegation_target": null, "baker_lp": 0.021214, "baker_bpy": "66,946.29", "o": 10, "order": 11}, {"index": 55006, "account": "4D44RYigFqPkABrRAHXSBBQqG4VNhXEsyJrt2GH6V2H8tS1tN3", "nonce": 17, "credential_creation_date": "2021-09-01", "credential_valid_to_date": "2026-09-01", "credential_count": 6, "total_balance": 88373934.421728, "unlocked_balance": 79413002.979505, "locked_balance": 8960931.442223, "baker_id": 1915.0, "staked_amount": 88373934.216821, "restake_earnings": true, "pool_status": "openForAll", "pool_metadata_url": "https://amdax.com/en/concordium-delegating-stake/", "pool_transaction_commission": 0.1, "pool_finalization_commission": 1.0, "pool_baking_commission": 0.1, "delegation_target": null, "baker_lp": 0.017112, "baker_bpy": "54,001.37", "o": 11, "order": 12}, {"index": 28341, "account": "3bYDf2e6ijKCSctqkdLDTuwJ41zpZXrVyHu8ErJ75VBH4h24yR", "nonce": 90, "credential_creation_date": "2022-01-01", "credential_valid_to_date": "2027-01-01", "credential_count": 5, "total_balance": 94697667.428508, "unlocked_balance": 15919629.848508, "locked_balance": 78778037.58, "baker_id": 76935.0, "staked_amount": 86000000.0, "restake_earnings": false, "pool_status": "openForAll", "pool_metadata_url": "https://www.stakingkit.com", "pool_transaction_commission": 0.1, "pool_finalization_commission": 1.0, "pool_baking_commission": 0.1, "delegation_target": null, "baker_lp": 0.010879, "baker_bpy": "34,331.51", "o": 12, "order": 13}, {"index": 29507, "account": "3d4tsSiBrJXn2aiNHdfqMq2b9oGttoKn2LDCZbHHMm1WZi2c95", "nonce": 99, "credential_creation_date": "2022-01-01", "credential_valid_to_date": "2027-01-01", "credential_count": 5, "total_balance": 93915524.322249, "unlocked_balance": 15152056.716091, "locked_balance": 78763467.606158, "baker_id": 76933.0, "staked_amount": 86000000.0, "restake_earnings": false, "pool_status": "closedForAll", "pool_metadata_url": null, "pool_transaction_commission": 0.1, "pool_finalization_commission": 1.0, "pool_baking_commission": 0.1, "delegation_target": null, "baker_lp": 0.010865, "baker_bpy": "34,287.33", "o": 13, "order": 14}, {"index": 51090, "account": "47uKy77Ds7AEsTd7AAnyeesWL5wAyraVvafPEfhFw9dveuGym6", "nonce": 96, "credential_creation_date": "2022-01-01", "credential_valid_to_date": "2027-01-01", "credential_count": 5, "total_balance": 93727927.428731, "unlocked_balance": 14949889.848731, "locked_balance": 78778037.58, "baker_id": 76937.0, "staked_amount": 86000000.0, "restake_earnings": false, "pool_status": "closedForAll", "pool_metadata_url": null, "pool_transaction_commission": 0.1, "pool_finalization_commission": 1.0, "pool_baking_commission": 0.1, "delegation_target": null, "baker_lp": 0.010865, "baker_bpy": "34,287.33", "o": 14, "order": 15}, {"index": 41094, "account": "3taQTr2vfAQmaKgStN6qWBwqAYpjCJatcugY7NK8SHQvUscCA8", "nonce": 96, "credential_creation_date": "2022-01-01", "credential_valid_to_date": "2027-01-01", "credential_count": 5, "total_balance": 93785231.6447, "unlocked_balance": 15007194.0647, "locked_balance": 78778037.58, "baker_id": 76936.0, "staked_amount": 86000000.0, "restake_earnings": false, "pool_status": "closedForAll", "pool_metadata_url": null, "pool_transaction_commission": 0.1, "pool_finalization_commission": 1.0, "pool_baking_commission": 0.1, "delegation_target": null, "baker_lp": 0.010865, "baker_bpy": "34,287.33", "o": 15, "order": 16}, {"index": 37224, "account": "3oTmYTDG683bJvhMBCZd29SPcwpPsKmF8wc7XDL9zrsqpXC7mq", "nonce": 19, "credential_creation_date": "2021-11-01", "credential_valid_to_date": "2026-11-01", "credential_count": 1, "total_balance": 65085688.231229, "unlocked_balance": 20397599.570459, "locked_balance": 44688088.66077, "baker_id": 60203.0, "staked_amount": 62754977.315436, "restake_earnings": true, "pool_status": "openForAll", "pool_metadata_url": null, "pool_transaction_commission": 0.1, "pool_finalization_commission": 1.0, "pool_baking_commission": 0.1, "delegation_target": null, "baker_lp": 0.007958, "baker_bpy": "25,113.54", "o": 16, "order": 17}, {"index": 36821, "account": "3nxFD3fqtUG6YGAPbg2zBGa81Pt1SvNNTDjvvVakjvHVYw1biN", "nonce": 11, "credential_creation_date": "2021-09-01", "credential_valid_to_date": "2026-09-01", "credential_count": 6, "total_balance": 60827667.065631, "unlocked_balance": 51866735.623408, "locked_balance": 8960931.442223, "baker_id": 1916.0, "staked_amount": 60827666.475789, "restake_earnings": true, "pool_status": "openForAll", "pool_metadata_url": "https://amdax.com/en/concordium-delegating-stake/", "pool_transaction_commission": 0.1, "pool_finalization_commission": 1.0, "pool_baking_commission": 0.1, "delegation_target": null, "baker_lp": 0.008494, "baker_bpy": "26,805.03", "o": 17, "order": 18}, {"index": 51975, "account": "494XRkeP9mRHAe7o4bHWm5MEazuyJh9iZ2Nsn14bC1seNZ8yKR", "nonce": 8, "credential_creation_date": "2021-12-01", "credential_valid_to_date": "2026-12-01", "credential_count": 1, "total_balance": 55820110.514305, "unlocked_balance": 44670658.089859, "locked_balance": 11149452.424446, "baker_id": 71572.0, "staked_amount": 55807239.18342, "restake_earnings": true, "pool_status": "closedForAll", "pool_metadata_url": null, "pool_transaction_commission": 0.1, "pool_finalization_commission": 1.0, "pool_baking_commission": 0.1, "delegation_target": null, "baker_lp": 0.007048, "baker_bpy": "22,241.80", "o": 18, "order": 19}, {"index": 36313, "account": "3nHTHHrit4wNgCRFkdvfFnLTL6AhViUE143eR7a6pMfWiazGKZ", "nonce": 38, "credential_creation_date": "2022-01-01", "credential_valid_to_date": "2027-01-01", "credential_count": 1, "total_balance": 53342270.912945, "unlocked_balance": 8467085.528329, "locked_balance": 44875185.384616, "baker_id": 74596.0, "staked_amount": 53341986.458686, "restake_earnings": true, "pool_status": "closedForAll", "pool_metadata_url": null, "pool_transaction_commission": 0.1, "pool_finalization_commission": 1.0, "pool_baking_commission": 0.1, "delegation_target": null, "baker_lp": 0.006737, "baker_bpy": "21,260.36", "o": 19, "order": 20}, {"index": 10015, "account": "3B85HEnBzjFcLm2ZN6Ggb9ig7CWT4vsBXM9j46v8o94stmzv9L", "nonce": 10, "credential_creation_date": "2021-09-01", "credential_valid_to_date": "2026-09-01", "credential_count": 6, "total_balance": 48176032.652096, "unlocked_balance": 39215101.209873, "locked_balance": 8960931.442223, "baker_id": 1917.0, "staked_amount": 48176022.001802, "restake_earnings": true, "pool_status": "closedForAll", "pool_metadata_url": null, "pool_transaction_commission": 0.1, "pool_finalization_commission": 1.0, "pool_baking_commission": 0.1, "delegation_target": null, "baker_lp": 0.006085, "baker_bpy": "19,202.80", "o": 20, "order": 21}, {"index": 7791, "account": "38DmwVuAwtCpscipaKGgAY1fs1huZS66LNqgyiMPTNk1NrgTzN", "nonce": 10, "credential_creation_date": "2021-09-01", "credential_valid_to_date": "2026-09-01", "credential_count": 6, "total_balance": 47718092.8133, "unlocked_balance": 38757161.371077, "locked_balance": 8960931.442223, "baker_id": 1918.0, "staked_amount": 47717784.927446, "restake_earnings": true, "pool_status": "closedForAll", "pool_metadata_url": null, "pool_transaction_commission": 0.1, "pool_finalization_commission": 1.0, "pool_baking_commission": 0.1, "delegation_target": null, "baker_lp": 0.006027, "baker_bpy": "19,019.77", "o": 21, "order": 22}, {"index": 11586, "account": "3DLD6CpYYa41FmvYdjxTKBhgkM63NtHZGBjBPZgzgSArm1sueS", "nonce": 8, "credential_creation_date": "2021-09-01", "credential_valid_to_date": "2026-09-01", "credential_count": 6, "total_balance": 45898048.999177, "unlocked_balance": 36937117.556954, "locked_balance": 8960931.442223, "baker_id": 1919.0, "staked_amount": 45898040.296319, "restake_earnings": true, "pool_status": "closedForAll", "pool_metadata_url": null, "pool_transaction_commission": 0.1, "pool_finalization_commission": 1.0, "pool_baking_commission": 0.1, "delegation_target": null, "baker_lp": 0.005797, "baker_bpy": "18,293.94", "o": 22, "order": 23}, {"index": 54981, "account": "4D1xtS8ztmxvuHy3ddiVQDnv96nwDRBj5bgWZx9uixMppgndzv", "nonce": 45, "credential_creation_date": "2021-06-01", "credential_valid_to_date": "2026-06-01", "credential_count": 1, "total_balance": 31736749.566531, "unlocked_balance": 23884818.006531, "locked_balance": 7851931.56, "baker_id": 1030.0, "staked_amount": 31736176.600043, "restake_earnings": true, "pool_status": "closedForAll", "pool_metadata_url": null, "pool_transaction_commission": 0.1, "pool_finalization_commission": 1.0, "pool_baking_commission": 0.1, "delegation_target": null, "baker_lp": 0.004008, "baker_bpy": "12,648.29", "o": 23, "order": 24}, {"index": 36006, "account": "3mpvnZhWR6DJ4JLxbRFmhodvRZKdfTAXc8xeMNVGkRYXXH4ZJH", "nonce": 40, "credential_creation_date": "2022-03-01", "credential_valid_to_date": "2027-03-01", "credential_count": 1, "total_balance": 28900002.890789, "unlocked_balance": 2531918.307711, "locked_balance": 26368084.583078, "baker_id": 82702.0, "staked_amount": 28900000.0, "restake_earnings": false, "pool_status": "openForAll", "pool_metadata_url": null, "pool_transaction_commission": 0.1, "pool_finalization_commission": 1.0, "pool_baking_commission": 0.1, "delegation_target": null, "baker_lp": 0.0036509999999999, "baker_bpy": "11,521.68", "o": 24, "order": 25}, {"index": 49921, "account": "46KKpv3b68J4nfnQc1qA3X2QvcNc76cUqz5D4eULMk7SZKMgNB", "nonce": 4, "credential_creation_date": "2022-03-01", "credential_valid_to_date": "2027-03-01", "credential_count": 1, "total_balance": 24915739.173429, "unlocked_balance": 4634208.064197, "locked_balance": 20281531.109232, "baker_id": 82705.0, "staked_amount": 23969000.0, "restake_earnings": false, "pool_status": "closedForAll", "pool_metadata_url": null, "pool_transaction_commission": 0.1, "pool_finalization_commission": 1.0, "pool_baking_commission": 0.1, "delegation_target": null, "baker_lp": 0.003028, "baker_bpy": "9,555.64", "o": 25, "order": 26}, {"index": 70851, "account": "4a1weEUcaPka7ZPBEyZ6AndcdaxwKkUahZoABKYNWSYZ6eFtFT", "nonce": 8, "credential_creation_date": "2022-02-01", "credential_valid_to_date": "2027-02-01", "credential_count": 1, "total_balance": 20806041.166237, "unlocked_balance": 20806041.166237, "locked_balance": 0.0, "baker_id": 82274.0, "staked_amount": 20795176.269635, "restake_earnings": true, "pool_status": "closedForAll", "pool_metadata_url": null, "pool_transaction_commission": 0.1, "pool_finalization_commission": 1.0, "pool_baking_commission": 0.1, "delegation_target": null, "baker_lp": 0.002627, "baker_bpy": "8,290.18", "o": 26, "order": 27}, {"index": 5486, "account": "35AGYQC9ArExG1XsQtYrRgzNAMAeq9WN1mH7X2f7q5m7FmfZqx", "nonce": 4, "credential_creation_date": "2021-06-01", "credential_valid_to_date": "2026-06-01", "credential_count": 1, "total_balance": 21842546.813112, "unlocked_balance": 17251595.879774, "locked_balance": 4590950.933338, "baker_id": 748.0, "staked_amount": 20650000.0, "restake_earnings": false, "pool_status": "closedForAll", "pool_metadata_url": null, "pool_transaction_commission": 0.1, "pool_finalization_commission": 1.0, "pool_baking_commission": 0.1, "delegation_target": null, "baker_lp": 0.002609, "baker_bpy": "8,233.38", "o": 27, "order": 28}, {"index": 71761, "account": "4bEqdbhvMbcktqhQsiuaRA46ZEe7o8PNTuGj5KhwYhStcgbGde", "nonce": 49, "credential_creation_date": "2022-03-01", "credential_valid_to_date": "2027-03-01", "credential_count": 1, "total_balance": 20255069.581281, "unlocked_balance": 1.146665, "locked_balance": 20255068.434616, "baker_id": 82701.0, "staked_amount": 20255000.0, "restake_earnings": false, "pool_status": "openForAll", "pool_metadata_url": null, "pool_transaction_commission": 0.1, "pool_finalization_commission": 1.0, "pool_baking_commission": 0.1, "delegation_target": null, "baker_lp": 0.002559, "baker_bpy": "8,075.59", "o": 28, "order": 29}, {"index": 42374, "account": "3vE4c72bqeCegyUhNiebhvPXTGN1TQMCivAmdfZ1XqBrCutzzA", "nonce": 4, "credential_creation_date": "2022-04-01", "credential_valid_to_date": "2027-04-01", "credential_count": 1, "total_balance": 17911991.018295, "unlocked_balance": 2962701.633679, "locked_balance": 14949289.384616, "baker_id": 83002.0, "staked_amount": 17727436.48101, "restake_earnings": true, "pool_status": "closedForAll", "pool_metadata_url": null, "pool_transaction_commission": 0.1, "pool_finalization_commission": 1.0, "pool_baking_commission": 0.1, "delegation_target": null, "baker_lp": 0.0022389999999999, "baker_bpy": "7,065.75", "o": 29, "order": 30}, {"index": 43454, "account": "3wkjtUwE4UuHDHs8dFrz7HZ1RmPqsnJxAYWswErkHkEYVBWj5j", "nonce": 6, "credential_creation_date": "2022-01-01", "credential_valid_to_date": "2027-01-01", "credential_count": 1, "total_balance": 17813737.663692, "unlocked_balance": 14276587.943692, "locked_balance": 3537149.72, "baker_id": 73647.0, "staked_amount": 17039574.643078, "restake_earnings": true, "pool_status": "closedForAll", "pool_metadata_url": null, "pool_transaction_commission": 0.1, "pool_finalization_commission": 1.0, "pool_baking_commission": 0.1, "delegation_target": null, "baker_lp": 0.002152, "baker_bpy": "6,791.20", "o": 30, "order": 31}, {"index": 36177, "account": "3n6kiufrNDYaFgqaGAyLZitRwQqyxnWQybruygc3Cx8WUpEGk6", "nonce": 6, "credential_creation_date": "2021-06-01", "credential_valid_to_date": "2026-06-01", "credential_count": 1, "total_balance": 16506590.32798, "unlocked_balance": 13226825.516851, "locked_balance": 3279764.811129, "baker_id": 438.0, "staked_amount": 16505495.49866, "restake_earnings": true, "pool_status": "closedForAll", "pool_metadata_url": null, "pool_transaction_commission": 0.1, "pool_finalization_commission": 1.0, "pool_baking_commission": 0.1, "delegation_target": null, "baker_lp": 0.002085, "baker_bpy": "6,579.76", "o": 31, "order": 32}, {"index": 58895, "account": "4JG7grYgjAdnyA9nukGGU49ijmP1DKBQQGLppCMGW7BUSB2NnE", "nonce": 26, "credential_creation_date": "2021-08-01", "credential_valid_to_date": "2026-08-01", "credential_count": 1, "total_balance": 14117325.114752, "unlocked_balance": 9650268.950299, "locked_balance": 4467056.164453, "baker_id": 1883.0, "staked_amount": 14117227.929532, "restake_earnings": true, "pool_status": "closedForAll", "pool_metadata_url": null, "pool_transaction_commission": 0.1, "pool_finalization_commission": 1.0, "pool_baking_commission": 0.1, "delegation_target": null, "baker_lp": 0.0017829999999999, "baker_bpy": "5,626.72", "o": 32, "order": 33}, {"index": 48350, "account": "44Enrtf7pss6NG4st9ijtVAX5X1xgMh51B1DXJCaUoNjCQc4ZX", "nonce": 1099, "credential_creation_date": "2022-03-01", "credential_valid_to_date": "2027-03-01", "credential_count": 1, "total_balance": 13430752.820552, "unlocked_balance": 13430752.820552, "locked_balance": 0.0, "baker_id": 82826.0, "staked_amount": 13430535.97976, "restake_earnings": true, "pool_status": "openForAll", "pool_metadata_url": null, "pool_transaction_commission": 0.1, "pool_finalization_commission": 1.0, "pool_baking_commission": 0.1, "delegation_target": null, "baker_lp": 0.001567, "baker_bpy": "4,945.08", "o": 33, "order": 34}, {"index": 23028, "account": "3USgJaoLTTtLF7o23qjPP2Tuis3X6PTwCTbkCNd8B3nTvtVoSW", "nonce": 15, "credential_creation_date": "2022-01-01", "credential_valid_to_date": "2027-01-01", "credential_count": 1, "total_balance": 13325665.256869, "unlocked_balance": 2112726.410715, "locked_balance": 11212938.846154, "baker_id": 74730.0, "staked_amount": 13251665.0, "restake_earnings": false, "pool_status": "closedForAll", "pool_metadata_url": null, "pool_transaction_commission": 0.1, "pool_finalization_commission": 1.0, "pool_baking_commission": 0.1, "delegation_target": null, "baker_lp": 0.001674, "baker_bpy": "5,282.74", "o": 34, "order": 35}, {"index": 19755, "account": "3Q6auaCXY27S9cw7wWxnL9NLRKeZ98BuhxNSwogkHEbApxt18C", "nonce": 11, "credential_creation_date": "2022-01-01", "credential_valid_to_date": "2027-01-01", "credential_count": 1, "total_balance": 13317784.553386, "unlocked_balance": 2104845.707232, "locked_balance": 11212938.846154, "baker_id": 74771.0, "staked_amount": 13251660.0, "restake_earnings": false, "pool_status": "closedForAll", "pool_metadata_url": null, "pool_transaction_commission": 0.1, "pool_finalization_commission": 1.0, "pool_baking_commission": 0.1, "delegation_target": null, "baker_lp": 0.001674, "baker_bpy": "5,282.74", "o": 35, "order": 36}, {"index": 70341, "account": "4ZM4rmHztAkVMWVzCSvxckwxUSsAd5Sas1mbBenNpreePRYd6h", "nonce": 11, "credential_creation_date": "2022-01-01", "credential_valid_to_date": "2027-01-01", "credential_count": 1, "total_balance": 13322602.34702, "unlocked_balance": 2109663.500866, "locked_balance": 11212938.846154, "baker_id": 74770.0, "staked_amount": 13251660.0, "restake_earnings": false, "pool_status": "closedForAll", "pool_metadata_url": null, "pool_transaction_commission": 0.1, "pool_finalization_commission": 1.0, "pool_baking_commission": 0.1, "delegation_target": null, "baker_lp": 0.001674, "baker_bpy": "5,282.74", "o": 36, "order": 37}, {"index": 48066, "account": "43sPTsozscn3d2RbxHiaWy6Pp23KthNeNV6LKBhrco5SqoB3YW", "nonce": 12, "credential_creation_date": "2022-01-01", "credential_valid_to_date": "2027-01-01", "credential_count": 1, "total_balance": 13322273.353831, "unlocked_balance": 2109334.507677, "locked_balance": 11212938.846154, "baker_id": 74772.0, "staked_amount": 13251660.0, "restake_earnings": false, "pool_status": "closedForAll", "pool_metadata_url": null, "pool_transaction_commission": 0.1, "pool_finalization_commission": 1.0, "pool_baking_commission": 0.1, "delegation_target": null, "baker_lp": 0.001674, "baker_bpy": "5,282.74", "o": 37, "order": 38}, {"index": 63241, "account": "4Py6nA7BbXvSfVD2ju9aG1tqw5oEX66w8PL1xJPP78id8gw5ac", "nonce": 26, "credential_creation_date": "2021-06-01", "credential_valid_to_date": "2026-06-01", "credential_count": 1, "total_balance": 13239161.353069, "unlocked_balance": 13054659.699731, "locked_balance": 184501.653338, "baker_id": 704.0, "staked_amount": 13238241.272662, "restake_earnings": true, "pool_status": "openForAll", "pool_metadata_url": null, "pool_transaction_commission": 0.1, "pool_finalization_commission": 1.0, "pool_baking_commission": 0.1, "delegation_target": null, "baker_lp": 0.0016719999999999, "baker_bpy": "5,276.43", "o": 38, "order": 39}, {"index": 83982, "account": "4sNmzUZHf8i56SbSHHypzxwSVyS7CX2swTZpCLna6Mor6zGczf", "nonce": 6, "credential_creation_date": "2021-07-01", "credential_valid_to_date": "2026-07-01", "credential_count": 1, "total_balance": 13377994.577941, "unlocked_balance": 2624810.547171, "locked_balance": 10753184.03077, "baker_id": 1632.0, "staked_amount": 13186400.296664, "restake_earnings": true, "pool_status": "closedForAll", "pool_metadata_url": null, "pool_transaction_commission": 0.1, "pool_finalization_commission": 1.0, "pool_baking_commission": 0.1, "delegation_target": null, "baker_lp": 0.001665, "baker_bpy": "5,254.34", "o": 39, "order": 40}, {"index": 42899, "account": "3vyzKn8Gup52JFqNwvVgcHKXktqW5Bj82ATnfwATQZ7uJiCTpw", "nonce": 37, "credential_creation_date": "2021-11-01", "credential_valid_to_date": "2026-11-01", "credential_count": 1, "total_balance": 11695908.628778, "unlocked_balance": 9723860.17544, "locked_balance": 1972048.453338, "baker_id": 3059.0, "staked_amount": 11605037.790954, "restake_earnings": false, "pool_status": "openForAll", "pool_metadata_url": null, "pool_transaction_commission": 0.1, "pool_finalization_commission": 1.0, "pool_baking_commission": 0.1, "delegation_target": null, "baker_lp": 0.001466, "baker_bpy": "4,626.34", "o": 40, "order": 41}, {"index": 82178, "account": "4prsbJTqccDvcRHaQs25J1wKfDXGUhYdphcshPRffMGbVarLYo", "nonce": 14, "credential_creation_date": "2022-01-01", "credential_valid_to_date": "2027-01-01", "credential_count": 1, "total_balance": 12717285.361102, "unlocked_balance": 10090457.365541, "locked_balance": 2626827.995561, "baker_id": 73541.0, "staked_amount": 11229689.0, "restake_earnings": false, "pool_status": "openForAll", "pool_metadata_url": "https://virtualhive.io/", "pool_transaction_commission": 0.1, "pool_finalization_commission": 1.0, "pool_baking_commission": 0.1, "delegation_target": null, "baker_lp": 0.001599, "baker_bpy": "5,046.06", "o": 41, "order": 42}, {"index": 10654, "account": "3C31UHhkhuKTgkSsRW2a3EUwsMYALuQp6ZofNFX9xUb7n5JJ4Y", "nonce": 12, "credential_creation_date": "2022-02-01", "credential_valid_to_date": "2027-02-01", "credential_count": 3, "total_balance": 11104690.055707, "unlocked_balance": 2082658.440321, "locked_balance": 9022031.615386, "baker_id": 78475.0, "staked_amount": 10980000.0, "restake_earnings": false, "pool_status": "openForAll", "pool_metadata_url": null, "pool_transaction_commission": 0.1, "pool_finalization_commission": 1.0, "pool_baking_commission": 0.1, "delegation_target": null, "baker_lp": 0.00161, "baker_bpy": "5,080.77", "o": 42, "order": 43}, {"index": 7194, "account": "37S5Q3bDDaZr278vwK4Z1T9rbMoNSVFPjkos48W9Kz3kGJAiNg", "nonce": 7, "credential_creation_date": "2021-07-01", "credential_valid_to_date": "2026-07-01", "credential_count": 1, "total_balance": 10457624.419949, "unlocked_balance": 8245097.646611, "locked_balance": 2212526.773338, "baker_id": 1484.0, "staked_amount": 9935323.126259, "restake_earnings": true, "pool_status": "closedForAll", "pool_metadata_url": null, "pool_transaction_commission": 0.1, "pool_finalization_commission": 1.0, "pool_baking_commission": 0.1, "delegation_target": null, "baker_lp": 0.001255, "baker_bpy": "3,960.48", "o": 43, "order": 44}, {"index": 36334, "account": "3nKBk9SKxCnL8A4w4WPKp6NxiVcd5YNmEcCBxY4YVGfWU8i9Hp", "nonce": 12, "credential_creation_date": "2021-07-01", "credential_valid_to_date": "2026-07-01", "credential_count": 1, "total_balance": 10086869.388075, "unlocked_balance": 8322908.052514, "locked_balance": 1763961.335561, "baker_id": 1469.0, "staked_amount": 9888801.696839, "restake_earnings": true, "pool_status": "closedForAll", "pool_metadata_url": null, "pool_transaction_commission": 0.1, "pool_finalization_commission": 1.0, "pool_baking_commission": 0.1, "delegation_target": null, "baker_lp": 0.001249, "baker_bpy": "3,941.54", "o": 44, "order": 45}, {"index": 63811, "account": "4QhdAyofhufMDACBgRGJcP1S5RxZRc4LgRngF9QSaVtZSS89uJ", "nonce": 39, "credential_creation_date": "2021-06-01", "credential_valid_to_date": "2026-06-01", "credential_count": 1, "total_balance": 9836162.109477, "unlocked_balance": 9310659.351693, "locked_balance": 525502.757784, "baker_id": 393.0, "staked_amount": 9836148.321915, "restake_earnings": true, "pool_status": "openForAll", "pool_metadata_url": null, "pool_transaction_commission": 0.1, "pool_finalization_commission": 1.0, "pool_baking_commission": 0.1, "delegation_target": null, "baker_lp": 0.001242, "baker_bpy": "3,919.45", "o": 45, "order": 46}, {"index": 211, "account": "2x2u4CRmjMU47YJUHMvgrxAdhEtvrxamgRXkzpN3p1i2WhLWEG", "nonce": 7, "credential_creation_date": "2022-03-01", "credential_valid_to_date": "2027-03-01", "credential_count": 1, "total_balance": 6932414.635208, "unlocked_balance": 6932414.635208, "locked_balance": 0.0, "baker_id": 82626.0, "staked_amount": 6932412.818754, "restake_earnings": true, "pool_status": "closedForAll", "pool_metadata_url": null, "pool_transaction_commission": 0.1, "pool_finalization_commission": 1.0, "pool_baking_commission": 0.1, "delegation_target": null, "baker_lp": 0.0008759999999999, "baker_bpy": "2,764.45", "o": 46, "order": 47}, {"index": 64489, "account": "4Ras4xAx3zSo3gBC3ktzNSz81D51ugQbUurMYPAEj1se51ARLj", "nonce": 5, "credential_creation_date": "2021-08-01", "credential_valid_to_date": "2026-08-01", "credential_count": 1, "total_balance": 6752514.700357, "unlocked_balance": 1371709.346509, "locked_balance": 5380805.353848, "baker_id": 1801.0, "staked_amount": 6752445.174455, "restake_earnings": true, "pool_status": "openForAll", "pool_metadata_url": null, "pool_transaction_commission": 0.1, "pool_finalization_commission": 1.0, "pool_baking_commission": 0.1, "delegation_target": null, "baker_lp": 0.000853, "baker_bpy": "2,691.86", "o": 47, "order": 48}, {"index": 30447, "account": "3ePAca51vQDPRvMPc74X77P2kBRBy78v3fTe7KEBfLFh257oMh", "nonce": 9, "credential_creation_date": "2022-01-01", "credential_valid_to_date": "2027-01-01", "credential_count": 2, "total_balance": 6701024.996763, "unlocked_balance": 1294869.042915, "locked_balance": 5406155.953848, "baker_id": 76875.0, "staked_amount": 6679136.103894, "restake_earnings": true, "pool_status": "closedForAll", "pool_metadata_url": null, "pool_transaction_commission": 0.1, "pool_finalization_commission": 1.0, "pool_baking_commission": 0.1, "delegation_target": null, "baker_lp": 0.000844, "baker_bpy": "2,663.46", "o": 48, "order": 49}, {"index": 16861, "account": "3LFNRq68kxRCVqxaTXiPrSddzHNpjYBxSH3JH4GVGCVjwDJzJr", "nonce": 3, "credential_creation_date": "2022-04-01", "credential_valid_to_date": "2027-04-01", "credential_count": 1, "total_balance": 6563779.225925, "unlocked_balance": 5239344.412587, "locked_balance": 1324434.813338, "baker_id": 83028.0, "staked_amount": 6563729.375892, "restake_earnings": true, "pool_status": "closedForAll", "pool_metadata_url": null, "pool_transaction_commission": 0.1, "pool_finalization_commission": 1.0, "pool_baking_commission": 0.1, "delegation_target": null, "baker_lp": 0.000829, "baker_bpy": "2,616.13", "o": 49, "order": 50}]}}