{"config": {"view": {"continuousWidth": 400, "continuousHeight": 300}}, "data": {"name": "data-3cd2e967cbf0a1657c88624cd047d786"}, "mark": "bar", "encoding": {"color": {"field": "stakeType", "type": "nominal"}, "x": {"field": "value", "title": "Staked Amount", "type": "quantitative"}, "y": {"field": "bakerId", "sort": {"field": "order"}, "title": null, "type": "ordinal"}}, "height": 500, "title": {"text": "Baker accounts (top 50) - Staked amounts", "subtitle": "2023-03-15"}, "width": "container", "$schema": "https://vega.github.io/schema/vega-lite/v4.17.0.json", "datasets": {"data-3cd2e967cbf0a1657c88624cd047d786": [{"bakerId": 5, "order": 1, "o": 0, "index": 3, "stakeType": "Baker Stake", "value": 943514099.985015}, {"bakerId": 8, "order": 2, "o": 1, "index": 5, "stakeType": "Baker Stake", "value": 818737775.376882}, {"bakerId": 3, "order": 3, "o": 2, "index": 1, "stakeType": "Baker Stake", "value": 818358045.578603}, {"bakerId": 1, "order": 4, "o": 3, "index": 0, "stakeType": "Baker Stake", "value": 742650102.781755}, {"bakerId": 83078, "order": 5, "o": 4, "index": 140, "stakeType": "Baker Stake", "value": 714433488.543971}, {"bakerId": 83075, "order": 6, "o": 5, "index": 139, "stakeType": "Baker Stake", "value": 712218001.922938}, {"bakerId": 6, "order": 7, "o": 6, "index": 4, "stakeType": "Baker Stake", "value": 693633213.996099}, {"bakerId": 83079, "order": 8, "o": 7, "index": 141, "stakeType": "Baker Stake", "value": 392704115.465186}, {"bakerId": 84886, "order": 9, "o": 8, "index": 162, "stakeType": "Baker Stake", "value": 277490940.714392}, {"bakerId": 84885, "order": 10, "o": 9, "index": 161, "stakeType": "Baker Stake", "value": 269791698.785433}, {"bakerId": 4, "order": 11, "o": 10, "index": 2, "stakeType": "Baker Stake", "value": 209204041.730797}, {"bakerId": 76670, "order": 12, "o": 11, "index": 111, "stakeType": "Baker Stake", "value": 190471981.410501}, {"bakerId": 72532, "order": 13, "o": 12, "index": 93, "stakeType": "Baker Stake", "value": 178139775.30734}, {"bakerId": 1915, "order": 14, "o": 13, "index": 69, "stakeType": "Baker Stake", "value": 170004797.022885}, {"bakerId": 84882, "order": 15, "o": 14, "index": 160, "stakeType": "Baker Stake", "value": 102866391.5271}, {"bakerId": 82826, "order": 16, "o": 15, "index": 135, "stakeType": "Baker Stake", "value": 102119646.527429}, {"bakerId": 60203, "order": 17, "o": 16, "index": 89, "stakeType": "Baker Stake", "value": 68683895.279891}, {"bakerId": 1916, "order": 18, "o": 17, "index": 70, "stakeType": "Baker Stake", "value": 57944309.896342}, {"bakerId": 76933, "order": 19, "o": 18, "index": 112, "stakeType": "Baker Stake", "value": 51638136.954164}, {"bakerId": 76936, "order": 20, "o": 19, "index": 114, "stakeType": "Baker Stake", "value": 50131473.0}, {"bakerId": 76937, "order": 21, "o": 20, "index": 115, "stakeType": "Baker Stake", "value": 50130773.0}, {"bakerId": 82274, "order": 22, "o": 21, "index": 125, "stakeType": "Baker Stake", "value": 37429758.177576}, {"bakerId": 85223, "order": 23, "o": 22, "index": 166, "stakeType": "Baker Stake", "value": 37296053.308453}, {"bakerId": 83002, "order": 24, "o": 23, "index": 138, "stakeType": "Baker Stake", "value": 31194588.146803}, {"bakerId": 1030, "order": 25, "o": 24, "index": 31, "stakeType": "Baker Stake", "value": 29477929.304537}, {"bakerId": 82702, "order": 26, "o": 25, "index": 133, "stakeType": "Baker Stake", "value": 23999392.211943}, {"bakerId": 74596, "order": 27, "o": 26, "index": 104, "stakeType": "Baker Stake", "value": 20041679.826098}, {"bakerId": 82701, "order": 28, "o": 27, "index": 132, "stakeType": "Baker Stake", "value": 18989422.686362}, {"bakerId": 704, "order": 29, "o": 28, "index": 22, "stakeType": "Baker Stake", "value": 17923983.526712}, {"bakerId": 438, "order": 30, "o": 29, "index": 7, "stakeType": "Baker Stake", "value": 17704620.762925}, {"bakerId": 1632, "order": 31, "o": 30, "index": 59, "stakeType": "Baker Stake", "value": 14095432.719952}, {"bakerId": 74730, "order": 32, "o": 31, "index": 105, "stakeType": "Baker Stake", "value": 13251665.0}, {"bakerId": 74771, "order": 33, "o": 32, "index": 107, "stakeType": "Baker Stake", "value": 13251660.0}, {"bakerId": 74772, "order": 34, "o": 33, "index": 108, "stakeType": "Baker Stake", "value": 13251660.0}, {"bakerId": 74770, "order": 35, "o": 34, "index": 106, "stakeType": "Baker Stake", "value": 13251660.0}, {"bakerId": 86225, "order": 36, "o": 35, "index": 176, "stakeType": "Baker Stake", "value": 12460043.143515}, {"bakerId": 3059, "order": 37, "o": 36, "index": 75, "stakeType": "Baker Stake", "value": 12321310.162566}, {"bakerId": 1484, "order": 38, "o": 37, "index": 55, "stakeType": "Baker Stake", "value": 11424172.218944}, {"bakerId": 84292, "order": 39, "o": 38, "index": 152, "stakeType": "Baker Stake", "value": 11311137.074851}, {"bakerId": 84476, "order": 40, "o": 39, "index": 157, "stakeType": "Baker Stake", "value": 10605092.839919}, {"bakerId": 85192, "order": 41, "o": 40, "index": 165, "stakeType": "Baker Stake", "value": 10036481.362407}, {"bakerId": 73541, "order": 42, "o": 41, "index": 102, "stakeType": "Baker Stake", "value": 8606759.804267}, {"bakerId": 82626, "order": 43, "o": 42, "index": 130, "stakeType": "Baker Stake", "value": 7346439.540477}, {"bakerId": 1801, "order": 44, "o": 43, "index": 65, "stakeType": "Baker Stake", "value": 7148103.189669}, {"bakerId": 584, "order": 45, "o": 44, "index": 16, "stakeType": "Baker Stake", "value": 5562575.667283}, {"bakerId": 507, "order": 46, "o": 45, "index": 12, "stakeType": "Baker Stake", "value": 4717538.57645}, {"bakerId": 1304, "order": 47, "o": 46, "index": 48, "stakeType": "Baker Stake", "value": 4231670.853044}, {"bakerId": 1051, "order": 48, "o": 47, "index": 33, "stakeType": "Baker Stake", "value": 3498071.146568}, {"bakerId": 85879, "order": 49, "o": 48, "index": 173, "stakeType": "Baker Stake", "value": 2800000.0}, {"bakerId": 82599, "order": 50, "o": 49, "index": 129, "stakeType": "Baker Stake", "value": 2586595.308103}, {"bakerId": 5, "order": 1, "o": 0, "index": 3, "stakeType": "Delegated Stake", "value": 0.0}, {"bakerId": 8, "order": 2, "o": 1, "index": 5, "stakeType": "Delegated Stake", "value": 0.0}, {"bakerId": 3, "order": 3, "o": 2, "index": 1, "stakeType": "Delegated Stake", "value": 0.0}, {"bakerId": 1, "order": 4, "o": 3, "index": 0, "stakeType": "Delegated Stake", "value": 0.0}, {"bakerId": 83078, "order": 5, "o": 4, "index": 140, "stakeType": "Delegated Stake", "value": 0.0}, {"bakerId": 83075, "order": 6, "o": 5, "index": 139, "stakeType": "Delegated Stake", "value": 0.0}, {"bakerId": 6, "order": 7, "o": 6, "index": 4, "stakeType": "Delegated Stake", "value": 0.0}, {"bakerId": 83079, "order": 8, "o": 7, "index": 141, "stakeType": "Delegated Stake", "value": 0.0}, {"bakerId": 84886, "order": 9, "o": 8, "index": 162, "stakeType": "Delegated Stake", "value": 1894313.369699}, {"bakerId": 84885, "order": 10, "o": 9, "index": 161, "stakeType": "Delegated Stake", "value": 200301.777829}, {"bakerId": 4, "order": 11, "o": 10, "index": 2, "stakeType": "Delegated Stake", "value": 0.0}, {"bakerId": 76670, "order": 12, "o": 11, "index": 111, "stakeType": "Delegated Stake", "value": 4528018.589499}, {"bakerId": 72532, "order": 13, "o": 12, "index": 93, "stakeType": "Delegated Stake", "value": 0.0}, {"bakerId": 1915, "order": 14, "o": 13, "index": 69, "stakeType": "Delegated Stake", "value": 151253776.380769}, {"bakerId": 84882, "order": 15, "o": 14, "index": 160, "stakeType": "Delegated Stake", "value": 0.0}, {"bakerId": 82826, "order": 16, "o": 15, "index": 135, "stakeType": "Delegated Stake", "value": 31648322.249986}, {"bakerId": 60203, "order": 17, "o": 16, "index": 89, "stakeType": "Delegated Stake", "value": 0.0}, {"bakerId": 1916, "order": 18, "o": 17, "index": 70, "stakeType": "Delegated Stake", "value": 7384408.079316}, {"bakerId": 76933, "order": 19, "o": 18, "index": 112, "stakeType": "Delegated Stake", "value": 0.0}, {"bakerId": 76936, "order": 20, "o": 19, "index": 114, "stakeType": "Delegated Stake", "value": 0.0}, {"bakerId": 76937, "order": 21, "o": 20, "index": 115, "stakeType": "Delegated Stake", "value": 0.0}, {"bakerId": 82274, "order": 22, "o": 21, "index": 125, "stakeType": "Delegated Stake", "value": 0.0}, {"bakerId": 85223, "order": 23, "o": 22, "index": 166, "stakeType": "Delegated Stake", "value": 33590243.350193}, {"bakerId": 83002, "order": 24, "o": 23, "index": 138, "stakeType": "Delegated Stake", "value": 0.0}, {"bakerId": 1030, "order": 25, "o": 24, "index": 31, "stakeType": "Delegated Stake", "value": 2513752.970384}, {"bakerId": 82702, "order": 26, "o": 25, "index": 133, "stakeType": "Delegated Stake", "value": 1000607.788057}, {"bakerId": 74596, "order": 27, "o": 26, "index": 104, "stakeType": "Delegated Stake", "value": 0.0}, {"bakerId": 82701, "order": 28, "o": 27, "index": 132, "stakeType": "Delegated Stake", "value": 10577.313638}, {"bakerId": 704, "order": 29, "o": 28, "index": 22, "stakeType": "Delegated Stake", "value": 2076016.473288}, {"bakerId": 438, "order": 30, "o": 29, "index": 7, "stakeType": "Delegated Stake", "value": 0.0}, {"bakerId": 1632, "order": 31, "o": 30, "index": 59, "stakeType": "Delegated Stake", "value": 0.0}, {"bakerId": 74730, "order": 32, "o": 31, "index": 105, "stakeType": "Delegated Stake", "value": 0.0}, {"bakerId": 74771, "order": 33, "o": 32, "index": 107, "stakeType": "Delegated Stake", "value": 0.0}, {"bakerId": 74772, "order": 34, "o": 33, "index": 108, "stakeType": "Delegated Stake", "value": 0.0}, {"bakerId": 74770, "order": 35, "o": 34, "index": 106, "stakeType": "Delegated Stake", "value": 0.0}, {"bakerId": 86225, "order": 36, "o": 35, "index": 176, "stakeType": "Delegated Stake", "value": 3880606.199466}, {"bakerId": 3059, "order": 37, "o": 36, "index": 75, "stakeType": "Delegated Stake", "value": 693512.63406}, {"bakerId": 1484, "order": 38, "o": 37, "index": 55, "stakeType": "Delegated Stake", "value": 0.0}, {"bakerId": 84292, "order": 39, "o": 38, "index": 152, "stakeType": "Delegated Stake", "value": 266754.200246}, {"bakerId": 84476, "order": 40, "o": 39, "index": 157, "stakeType": "Delegated Stake", "value": 4391.199028}, {"bakerId": 85192, "order": 41, "o": 40, "index": 165, "stakeType": "Delegated Stake", "value": 3143423.657875}, {"bakerId": 73541, "order": 42, "o": 41, "index": 102, "stakeType": "Delegated Stake", "value": 3441872.530902}, {"bakerId": 82626, "order": 43, "o": 42, "index": 130, "stakeType": "Delegated Stake", "value": 0.0}, {"bakerId": 1801, "order": 44, "o": 43, "index": 65, "stakeType": "Delegated Stake", "value": 27643.820169}, {"bakerId": 584, "order": 45, "o": 44, "index": 16, "stakeType": "Delegated Stake", "value": 0.0}, {"bakerId": 507, "order": 46, "o": 45, "index": 12, "stakeType": "Delegated Stake", "value": 0.0}, {"bakerId": 1304, "order": 47, "o": 46, "index": 48, "stakeType": "Delegated Stake", "value": 0.0}, {"bakerId": 1051, "order": 48, "o": 47, "index": 33, "stakeType": "Delegated Stake", "value": 52890.312835}, {"bakerId": 85879, "order": 49, "o": 48, "index": 173, "stakeType": "Delegated Stake", "value": 0.0}, {"bakerId": 82599, "order": 50, "o": 49, "index": 129, "stakeType": "Delegated Stake", "value": 0.0}]}}