{"config": {"view": {"continuousWidth": 400, "continuousHeight": 300}}, "layer": [{"mark": "bar", "encoding": {"color": {"field": "restake_earnings", "legend": {"direction": "horizontal", "fillColor": "white", "legendX": 100, "legendY": 450, "orient": "none", "title": "Restake Earnings", "titleAnchor": "middle"}, "scale": {"domain": ["true", "false"], "range": ["#70B785", "#549FF2"]}, "type": "nominal"}, "x": {"field": "staked_amount", "title": "Staked Amount", "type": "quantitative"}, "y": {"field": "order", "title": null, "type": "ordinal"}}, "height": 500, "title": {"text": "Baker accounts (top 50) - Staked amounts", "subtitle": "2022-01-07"}, "width": "container"}, {"mark": {"type": "text", "align": "left", "baseline": "middle", "dx": 10, "dy": 2}, "encoding": {"color": {"field": "restake_earnings", "legend": {"direction": "horizontal", "fillColor": "white", "legendX": 100, "legendY": 450, "orient": "none", "title": "Restake Earnings", "titleAnchor": "middle"}, "scale": {"domain": ["true", "false"], "range": ["#70B785", "#549FF2"]}, "type": "nominal"}, "text": {"field": "baker_id", "type": "ordinal"}, "x": {"field": "staked_amount", "title": "Staked Amount", "type": "quantitative"}, "y": {"field": "order", "title": null, "type": "ordinal"}}, "height": 500, "title": {"text": "Baker accounts (top 50) - Staked amounts", "subtitle": "2022-01-07"}, "width": "container"}], "data": {"name": "data-0a8ff730726cf58eaea44b205577a689"}, "$schema": "https://vega.github.io/schema/vega-lite/v4.17.0.json", "datasets": {"data-0a8ff730726cf58eaea44b205577a689": [{"index": 21666, "account": "3XSLuJcXg6xEua6iBPnWacc3iWh93yEDMCqX8FbE3RDSbEnT9P", "nonce": 1, "credential_creation_date": "2021-05-01", "credential_valid_to_date": "2026-05-01", "credential_count": 7, "total_balance": 1684280607.416969, "unlocked_balance": 1684280607.416969, "locked_balance": 0.0, "baker_id": 7.0, "staked_amount": 1684279607.416969, "restake_earnings": true, "baker_lp": 0.324386, "baker_bpy": "1,023,684.36", "o": 0, "order": 1}, {"index": 52686, "account": "4MPJybKC9Kz7kw9KNyLHhuAEt4ZTxLsd3DBDbxtKdUiv4fXqVN", "nonce": 1, "credential_creation_date": "2021-05-01", "credential_valid_to_date": "2026-05-01", "credential_count": 7, "total_balance": 603192983.908115, "unlocked_balance": 603192983.908115, "locked_balance": 0.0, "baker_id": 6.0, "staked_amount": 603191983.908115, "restake_earnings": true, "baker_lp": 0.116173, "baker_bpy": "366,614.11", "o": 1, "order": 2}, {"index": 43961, "account": "47xTHwtFra1d4Mq4DYZuZYJEYrDXY34C4CGkTTzT6eiwjEczuT", "nonce": 1, "credential_creation_date": "2021-05-01", "credential_valid_to_date": "2026-05-01", "credential_count": 7, "total_balance": 440760339.376911, "unlocked_balance": 440760339.376911, "locked_balance": 0.0, "baker_id": 1.0, "staked_amount": 440759339.376911, "restake_earnings": true, "baker_lp": 0.0848889999999999, "baker_bpy": "267,889.31", "o": 2, "order": 3}, {"index": 32121, "account": "3ofwYFAkgV59BsHqzmiWyRmmKRB5ZzrPfbmx5nup24cE53jNX5", "nonce": 1, "credential_creation_date": "2021-05-01", "credential_valid_to_date": "2026-05-01", "credential_count": 7, "total_balance": 440415578.423833, "unlocked_balance": 440415578.423833, "locked_balance": 0.0, "baker_id": 5.0, "staked_amount": 440414578.423833, "restake_earnings": true, "baker_lp": 0.084822, "baker_bpy": "267,677.87", "o": 3, "order": 4}, {"index": 44902, "account": "49SJ6R6T9zo1C5cLVyxbwAuZC3EcDB9a78vSQYm3ZLA2y2eojM", "nonce": 1, "credential_creation_date": "2021-05-01", "credential_valid_to_date": "2026-05-01", "credential_count": 7, "total_balance": 440378518.940453, "unlocked_balance": 440378518.940453, "locked_balance": 0.0, "baker_id": 0.0, "staked_amount": 440377518.940453, "restake_earnings": true, "baker_lp": 0.084816, "baker_bpy": "267,658.94", "o": 4, "order": 5}, {"index": 10818, "account": "3EctbG8WaQkTqZb1NTJPAFnqmuhvW62pQbywvqb9VeyqaFZdzN", "nonce": 1, "credential_creation_date": "2021-05-01", "credential_valid_to_date": "2026-05-01", "credential_count": 7, "total_balance": 440257878.139746, "unlocked_balance": 440257878.139746, "locked_balance": 0.0, "baker_id": 4.0, "staked_amount": 440256878.139746, "restake_earnings": true, "baker_lp": 0.084792, "baker_bpy": "267,583.20", "o": 5, "order": 6}, {"index": 62880, "account": "4d13WVDNKVGDUxRUb1PRQAJyTwWSVcjWS7uwZ1oqmDm5icQEPT", "nonce": 1, "credential_creation_date": "2021-05-01", "credential_valid_to_date": "2026-05-01", "credential_count": 7, "total_balance": 440229158.408286, "unlocked_balance": 440229158.408286, "locked_balance": 0.0, "baker_id": 3.0, "staked_amount": 440228158.408286, "restake_earnings": true, "baker_lp": 0.084786, "baker_bpy": "267,564.27", "o": 6, "order": 7}, {"index": 9556, "account": "3CbvrNVpcHpL7tyT2mhXxQwNWHiPNYEJRgp3CMgEcMyXivms6B", "nonce": 1, "credential_creation_date": "2021-05-01", "credential_valid_to_date": "2026-05-01", "credential_count": 7, "total_balance": 440125877.798391, "unlocked_balance": 440125877.798391, "locked_balance": 0.0, "baker_id": 2.0, "staked_amount": 440124877.798391, "restake_earnings": true, "baker_lp": 0.084767, "baker_bpy": "267,504.31", "o": 7, "order": 8}, {"index": 31975, "account": "3oTmYTDG683bJvhMBCZd29SPcwpPsKmF8wc7XDL9zrsqpXC7mq", "nonce": 5, "credential_creation_date": "2021-11-01", "credential_valid_to_date": "2026-11-01", "credential_count": 1, "total_balance": 52848172.139949, "unlocked_balance": 34976.449949, "locked_balance": 52813195.69, "baker_id": 60203.0, "staked_amount": 52813000.0, "restake_earnings": false, "baker_lp": 0.010172, "baker_bpy": "32,100.39", "o": 8, "order": 9}, {"index": 47275, "account": "4D44RYigFqPkABrRAHXSBBQqG4VNhXEsyJrt2GH6V2H8tS1tN3", "nonce": 4, "credential_creation_date": "2021-09-01", "credential_valid_to_date": "2026-09-01", "credential_count": 5, "total_balance": 51019161.032943, "unlocked_balance": 10694969.542943, "locked_balance": 40324191.49, "baker_id": 1915.0, "staked_amount": 40345942.775902, "restake_earnings": true, "baker_lp": 0.00777, "baker_bpy": "24,520.26", "o": 9, "order": 10}, {"index": 31643, "account": "3nxFD3fqtUG6YGAPbg2zBGa81Pt1SvNNTDjvvVakjvHVYw1biN", "nonce": 5, "credential_creation_date": "2021-09-01", "credential_valid_to_date": "2026-09-01", "credential_count": 5, "total_balance": 40332374.82073, "unlocked_balance": 8183.33073, "locked_balance": 40324191.49, "baker_id": 1916.0, "staked_amount": 40332364.857897, "restake_earnings": true, "baker_lp": 0.007768, "baker_bpy": "24,513.94", "o": 10, "order": 11}, {"index": 6715, "account": "38DmwVuAwtCpscipaKGgAY1fs1huZS66LNqgyiMPTNk1NrgTzN", "nonce": 5, "credential_creation_date": "2021-09-01", "credential_valid_to_date": "2026-09-01", "credential_count": 5, "total_balance": 40331403.47465, "unlocked_balance": 7211.98465, "locked_balance": 40324191.49, "baker_id": 1918.0, "staked_amount": 40331393.511817, "restake_earnings": true, "baker_lp": 0.007768, "baker_bpy": "24,513.94", "o": 11, "order": 12}, {"index": 8632, "account": "3B85HEnBzjFcLm2ZN6Ggb9ig7CWT4vsBXM9j46v8o94stmzv9L", "nonce": 5, "credential_creation_date": "2021-09-01", "credential_valid_to_date": "2026-09-01", "credential_count": 5, "total_balance": 40331329.196967, "unlocked_balance": 7137.706967, "locked_balance": 40324191.49, "baker_id": 1917.0, "staked_amount": 40331319.234134, "restake_earnings": true, "baker_lp": 0.007768, "baker_bpy": "24,513.94", "o": 12, "order": 13}, {"index": 9985, "account": "3DLD6CpYYa41FmvYdjxTKBhgkM63NtHZGBjBPZgzgSArm1sueS", "nonce": 5, "credential_creation_date": "2021-09-01", "credential_valid_to_date": "2026-09-01", "credential_count": 5, "total_balance": 40330714.6547, "unlocked_balance": 6523.1647, "locked_balance": 40324191.49, "baker_id": 1919.0, "staked_amount": 40330704.691867, "restake_earnings": true, "baker_lp": 0.007767, "baker_bpy": "24,510.79", "o": 13, "order": 14}, {"index": 21848, "account": "3Xhdwp4Y2dXTTKaCs1G4QNy7vtUtmZDRzwtex1hSqw2ekUK7ZE", "nonce": 7, "credential_creation_date": "2022-01-01", "credential_valid_to_date": "2027-01-01", "credential_count": 3, "total_balance": 7944541.291059, "unlocked_balance": 404410.911059, "locked_balance": 7540130.38, "baker_id": 72532.0, "staked_amount": 7943557.272174, "restake_earnings": true, "baker_lp": 0.00153, "baker_bpy": "4,828.31", "o": 14, "order": 15}, {"index": 62763, "account": "4cptmQbfj2hcudEdXzTmt9hCzCySPxEpMoF4nj7qfqJfWNFmdu", "nonce": 5, "credential_creation_date": "2021-12-01", "credential_valid_to_date": "2026-12-01", "credential_count": 1, "total_balance": 30474.625522, "unlocked_balance": 30474.625522, "locked_balance": 0.0, "baker_id": 44954.0, "staked_amount": 30269.353776, "restake_earnings": true, "baker_lp": 5.999999999999999e-06, "baker_bpy": "18.93", "o": 15, "order": 16}, {"index": 35078, "account": "3tCzQbzpFiKpwwrc1ZxM7b9N9qbCTrhockSjnxvGeaRbPP8KCQ", "nonce": 2, "credential_creation_date": "2021-10-01", "credential_valid_to_date": "2026-10-01", "credential_count": 1, "total_balance": 20639.585083, "unlocked_balance": 20639.585083, "locked_balance": 0.0, "baker_id": 41492.0, "staked_amount": 20638.689084, "restake_earnings": true, "baker_lp": 4e-06, "baker_bpy": "12.62", "o": 16, "order": 17}, {"index": 25664, "account": "3dUfqYpEMJz49UstE2kNi5hkq8rgupTjbTGBtMBPBTMXsYYXDr", "nonce": 2, "credential_creation_date": "2021-11-01", "credential_valid_to_date": "2026-11-01", "credential_count": 1, "total_balance": 16405.086516, "unlocked_balance": 16405.086516, "locked_balance": 0.0, "baker_id": 2205.0, "staked_amount": 16400.0, "restake_earnings": true, "baker_lp": 3e-06, "baker_bpy": "9.47", "o": 17, "order": 18}, {"index": 60646, "account": "4ZfvU8atfVAdUeHWrJfFMNv5NPpRgiTzBWjrQWazDDtPLV9rds", "nonce": 3, "credential_creation_date": "2021-08-01", "credential_valid_to_date": "2026-08-01", "credential_count": 1, "total_balance": 15981.532541, "unlocked_balance": 15981.532541, "locked_balance": 0.0, "baker_id": 1847.0, "staked_amount": 15971.894376, "restake_earnings": true, "baker_lp": 3e-06, "baker_bpy": "9.47", "o": 18, "order": 19}, {"index": 5413, "account": "36DnwxSRBfLuNsCPnGkCbsWfDnhWA5A8HsTiUgvv6nuBCsh51V", "nonce": 5, "credential_creation_date": "2021-12-01", "credential_valid_to_date": "2026-12-01", "credential_count": 1, "total_balance": 14958.368276, "unlocked_balance": 14958.368276, "locked_balance": 0.0, "baker_id": 35027.0, "staked_amount": 14860.374911, "restake_earnings": true, "baker_lp": 3e-06, "baker_bpy": "9.47", "o": 19, "order": 20}, {"index": 6511, "account": "37v57HDNaoTZeRcCEruBSZzYzFYsutZ8ov4NVzeDf4nzyhoRhP", "nonce": 2, "credential_creation_date": "2022-01-01", "credential_valid_to_date": "2027-01-01", "credential_count": 1, "total_balance": 14116.165999, "unlocked_balance": 14116.165999, "locked_balance": 0.0, "baker_id": 72397.0, "staked_amount": 14000.0, "restake_earnings": true, "baker_lp": 3e-06, "baker_bpy": "9.47", "o": 20, "order": 21}, {"index": 28548, "account": "3hxLuF67LmdXWRyL2aF9g8SKMi8mptghkwmpyFutphk7Uqgaom", "nonce": 2, "credential_creation_date": "2021-12-01", "credential_valid_to_date": "2026-12-01", "credential_count": 1, "total_balance": 14070.618859, "unlocked_balance": 14070.618859, "locked_balance": 0.0, "baker_id": 40374.0, "staked_amount": 14000.0, "restake_earnings": true, "baker_lp": 3e-06, "baker_bpy": "9.47", "o": 21, "order": 22}, {"index": 61786, "account": "4bSR9AYcp8kMuwVwGjZQTfwwaxVSptBcpUZKYDN13wMA6u6xNJ", "nonce": 2, "credential_creation_date": "2021-08-01", "credential_valid_to_date": "2026-08-01", "credential_count": 1, "total_balance": 3240.453094, "unlocked_balance": 3240.453094, "locked_balance": 0.0, "baker_id": 1816.0, "staked_amount": 3140.498814, "restake_earnings": true, "baker_lp": 0.0, "baker_bpy": "0.00", "o": 22, "order": 23}, {"index": 26014, "account": "3e4k3jejVcMDKUvtbHXzey5GCrDeagJXD7UYWf1m4PiHPp84FJ", "nonce": 13, "credential_creation_date": "2021-09-01", "credential_valid_to_date": "2026-09-01", "credential_count": 1, "total_balance": 3183.445385, "unlocked_balance": 3183.445385, "locked_balance": 0.0, "baker_id": 1900.0, "staked_amount": 2900.0, "restake_earnings": true, "baker_lp": 0.0, "baker_bpy": "0.00", "o": 23, "order": 24}, {"index": 49125, "account": "4FyFDVzHW2kc9VXcCtCVv5JpNysCddbVCz8uULZ6Vz4WoY1UJB", "nonce": 2, "credential_creation_date": "2021-07-01", "credential_valid_to_date": "2026-07-01", "credential_count": 1, "total_balance": 2885.59822, "unlocked_balance": 2885.59822, "locked_balance": 0.0, "baker_id": 1531.0, "staked_amount": 2785.64394, "restake_earnings": true, "baker_lp": 0.0, "baker_bpy": "0.00", "o": 24, "order": 25}, {"index": 41806, "account": "44bxoGippBqpgseaiYPFnYgi5J5q58bQKfpQFeGbY9DHmDPD78", "nonce": 1, "credential_creation_date": "2021-05-01", "credential_valid_to_date": "2026-05-01", "credential_count": 7, "total_balance": 3882619997.0, "unlocked_balance": 3882619997.0, "locked_balance": 0.0, "baker_id": 8.0, "staked_amount": 0.0, "restake_earnings": true, "baker_lp": 0.0, "baker_bpy": "0.00", "o": 25, "order": 26}]}}